esdn_sensing/__init__.py
esdn_sensing/break_beam.py
esdn_sensing/hydros.py
esdn_sensing/ltr303.py
esdn_sensing/ltr390.py
esdn_sensing/minigps.py
esdn_sensing/opc.py
esdn_sensing/pm25.py
esdn_sensing/sen5x.py
esdn_sensing/sensor_error.py
esdn_sensing/stemma_soil.py
esdn_sensing/us100.py
esdn_sensing/vl6180x.py
esdn_sensing-0.3.3.dist-info/LICENSE
esdn_sensing-0.3.3.dist-info/METADATA
esdn_sensing-0.3.3.dist-info/WHEEL
esdn_sensing-0.3.3.dist-info/top_level.txt
esdn_sensing-0.3.3.dist-info/RECORD
